docs/conf.py
docs/dev/example/open.py
drb/drivers/zip/__init__.py
drb/drivers/zip/_version.py
drb/drivers/zip/zip.py
drb/exceptions/zip.py
drb/topics/zip/__init__.py
drb/topics/zip/cortex.yml
tests/__init__.py
tests/test_impl.py
tests/test_signature.py
tests/test_zip.py
drb_driver_zip-1.3.1.dist-info/LICENCE.txt
drb_driver_zip-1.3.1.dist-info/METADATA
drb_driver_zip-1.3.1.dist-info/WHEEL
drb_driver_zip-1.3.1.dist-info/entry_points.txt
drb_driver_zip-1.3.1.dist-info/top_level.txt
drb_driver_zip-1.3.1.dist-info/RECORD
