Metadata-Version: 2.1
Name: drb-driver-zip
Version: 1.3.1
Summary: DRB driver Zip
Home-page: https://gitlab.com/drb-python/impl/zip
Author: GAEL Systems
Author-email: drb-python@gael.fr
License: LGPLv3
Project-URL: Documentation, https://drb-python.gitlab.io/impl/zip
Project-URL: Source, https://gitlab.com/drb-python/impl/zip
Classifier: Programming Language :: Python :: 3.8
Classifier: License :: OSI Approved :: GNU Lesser General Public License v3 (LGPLv3)
Classifier: Operating System :: OS Independent
Requires-Python: >=3.8
License-File: LICENCE.txt
Requires-Dist: drb ~=2.2.0
